pyparallels/__init__.py
pyparallels/core.py
pyparallels-0.1.0.dist-info/METADATA
pyparallels-0.1.0.dist-info/WHEEL
pyparallels-0.1.0.dist-info/top_level.txt
pyparallels-0.1.0.dist-info/RECORD
